vector_rag/__init__.py
vector_rag/api/__init__.py
vector_rag/chunking/__init__.py
vector_rag/chunking/base_chunker.py
vector_rag/chunking/line_chunker.py
vector_rag/chunking/size_chunker.py
vector_rag/chunking/word_chunker.py
vector_rag/config.py
vector_rag/db/__init__.py
vector_rag/db/base_file_handler.py
vector_rag/db/db_file_handler.py
vector_rag/db/db_model.py
vector_rag/db/dimension_utils.py
vector_rag/embeddings/__init__.py
vector_rag/embeddings/base.py
vector_rag/embeddings/mock_embedder.py
vector_rag/embeddings/openai_embedder.py
vector_rag/embeddings/sentence_transformers_embedder.py
vector_rag/logging_config.py
vector_rag/model.py
vector_rag-0.1.1.dist-info/LICENSE
vector_rag-0.1.1.dist-info/METADATA
vector_rag-0.1.1.dist-info/WHEEL
vector_rag-0.1.1.dist-info/RECORD
