Metadata-Version: 2.3
Name: vector-rag
Version: 0.1.1
Summary: RAG (Retrieval-Augmented Generation) System
Author: Richard Hightower
Author-email: richardhightower@gmail.com
Requires-Python: >=3.10,<3.13
Classifier: Programming Language :: Python :: 3
Classifier: Programming Language :: Python :: 3.10
Classifier: Programming Language :: Python :: 3.11
Classifier: Programming Language :: Python :: 3.12
Requires-Dist: openai (>=1.58.1,<2.0.0)
Requires-Dist: pgvector (>=0.3.6,<0.4.0)
Requires-Dist: psycopg2-binary (>=2.9.10,<3.0.0)
Requires-Dist: python-dotenv (>=1.0.1,<2.0.0)
Requires-Dist: sqlalchemy (>=2.0.36,<3.0.0)
Project-URL: Repository, https://github.com/RichardHightower/rag
